scimodels/__init__.py
scimodels/__version__.py
scimodels/dependencies.py
scimodels/exceptions.py
scimodels/loaders.py
scimodels/response.py
scimodels/temp.py
scimodels/abstract/__init__.py
scimodels/abstract/apimodel.py
scimodels/abstract/batchmodel.py
scimodels/abstract/modelbase.py
scimodels/models/__init__.py
scimodels/models/openai.py
scimodels/models/openai_batch.py
scimodels/models/vllm.py
scimodels-0.1.3.dist-info/licenses/LICENSE
scimodels-0.1.3.dist-info/METADATA
scimodels-0.1.3.dist-info/WHEEL
scimodels-0.1.3.dist-info/top_level.txt
scimodels-0.1.3.dist-info/RECORD
