Metadata-Version: 2.4
Name: scimodels
Version: 0.1.3
Summary: A minimal module for using different LLMs and APIs effortlessly
Author: Nikolay Georgiev
Author-email: Nikolay Georgiev <nygeorgiev@protonmail.com>
License: MIT
Project-URL: Repository, https://github.com/nygeorgiev/scimodels
Requires-Python: >=3.11
License-File: LICENSE
Requires-Dist: tqdm
Dynamic: license-file
